[
  {
    "created_date": "2023-05-30",
    "quantity": "5",
    "positive": "1",
    "negative": "1"
  },
  {
    "created_date": "2023-05-31",
    "quantity": "7",
    "positive": "3",
    "negative": "2"
  },
  {
    "created_date": "2023-06-01",
    "quantity": "8",
    "positive": "5",
    "negative": "1"
  },
  {
    "created_date": "2023-06-02",
    "quantity": "8",
    "positive": "0",
    "negative": "0"
  },
  {
    "created_date": "2023-06-03",
    "quantity": "7",
    "positive": "4",
    "negative": "1"
  },
  {
    "created_date": "2023-06-04",
    "quantity": "8",
    "positive": "8",
    "negative": "0"
  },
  {
    "created_date": "2023-06-05",
    "quantity": "14",
    "positive": "5",
    "negative": "5"
  },
  {
    "created_date": "2023-06-06",
    "quantity": "10",
    "positive": "10",
    "negative": "0"
  },
  {
    "created_date": "2023-06-07",
    "quantity": "9",
    "positive": "5",
    "negative": "0"
  },
  {
    "created_date": "2023-06-08",
    "quantity": "6",
    "positive": "3",
    "negative": "0"
  },
  {
    "created_date": "2023-06-09",
    "quantity": "5",
    "positive": "5",
    "negative": "0"
  },
  {
    "created_date": "2023-06-10",
    "quantity": "23",
    "positive": "21",
    "negative": "1"
  },
  {
    "created_date": "2023-06-11",
    "quantity": "4",
    "positive": "3",
    "negative": "1"
  },
  {
    "created_date": "2023-06-12",
    "quantity": "9",
    "positive": "3",
    "negative": "2"
  },
  {
    "created_date": "2023-06-13",
    "quantity": "8",
    "positive": "8",
    "negative": "0"
  },
  {
    "created_date": "2023-06-14",
    "quantity": "17",
    "positive": "8",
    "negative": "7"
  },
  {
    "created_date": "2023-06-15",
    "quantity": "4",
    "positive": "3",
    "negative": "1"
  },
  {
    "created_date": "2023-06-16",
    "quantity": "8",
    "positive": "8",
    "negative": "0"
  },
  {
    "created_date": "2023-06-17",
    "quantity": "15",
    "positive": "0",
    "negative": "0"
  },
  {
    "created_date": "2023-06-18",
    "quantity": "7",
    "positive": "5",
    "negative": "0"
  },
  {
    "created_date": "2023-06-19",
    "quantity": "8",
    "positive": "1",
    "negative": "1"
  },
  {
    "created_date": "2023-06-20",
    "quantity": "9",
    "positive": "5",
    "negative": "4"
  },
  {
    "created_date": "2023-06-21",
    "quantity": "14",
    "positive": "8",
    "negative": "4"
  },
  {
    "created_date": "2023-06-22",
    "quantity": "7",
    "positive": "7",
    "negative": "0"
  },
  {
    "created_date": "2023-06-23",
    "quantity": "8",
    "positive": "8",
    "negative": "0"
  },
  {
    "created_date": "2023-06-24",
    "quantity": "14",
    "positive": "8",
    "negative": "5"
  },
  {
    "created_date": "2023-06-25",
    "quantity": "2",
    "positive": "2",
    "negative": "0"
  },
  {
    "created_date": "2023-06-26",
    "quantity": "8",
    "positive": "7",
    "negative": "0"
  },
  {
    "created_date": "2023-06-27",
    "quantity": "10",
    "positive": "7",
    "negative": "1"
  },
  {
    "created_date": "2023-06-28",
    "quantity": "7",
    "positive": "7",
    "negative": "0"
  },
  {
    "created_date": "2023-06-29",
    "quantity": "13",
    "positive": "6",
    "negative": "0"
  },
  {
    "created_date": "2023-06-30",
    "quantity": "6",
    "positive": "0",
    "negative": "0"
  },
  {
    "created_date": "2023-07-01",
    "quantity": "1",
    "positive": "1",
    "negative": "0"
  },
  {
    "created_date": "2023-07-02",
    "quantity": "12",
    "positive": "2",
    "negative": "2"
  },
  {
    "created_date": "2023-07-03",
    "quantity": "11",
    "positive": "0",
    "negative": "0"
  },
  {
    "created_date": "2023-07-04",
    "quantity": "4",
    "positive": "3",
    "negative": "1"
  },
  {
    "created_date": "2023-07-05",
    "quantity": "5",
    "positive": "2",
    "negative": "0"
  },
  {
    "created_date": "2023-07-06",
    "quantity": "4",
    "positive": "0",
    "negative": "0"
  },
  {
    "created_date": "2023-07-07",
    "quantity": "7",
    "positive": "2",
    "negative": "2"
  },
  {
    "created_date": "2023-07-08",
    "quantity": "8",
    "positive": "6",
    "negative": "2"
  },
  {
    "created_date": "2023-07-09",
    "quantity": "4",
    "positive": "1",
    "negative": "1"
  },
  {
    "created_date": "2023-07-10",
    "quantity": "8",
    "positive": "8",
    "negative": "0"
  },
  {
    "created_date": "2023-07-11",
    "quantity": "14",
    "positive": "14",
    "negative": "0"
  },
  {
    "created_date": "2023-07-12",
    "quantity": "21",
    "positive": "20",
    "negative": "1"
  },
  {
    "created_date": "2023-07-13",
    "quantity": "17",
    "positive": "10",
    "negative": "5"
  },
  {
    "created_date": "2023-07-14",
    "quantity": "9",
    "positive": "0",
    "negative": "0"
  },
  {
    "created_date": "2023-07-15",
    "quantity": "7",
    "positive": "0",
    "negative": "0"
  },
  {
    "created_date": "2023-07-16",
    "quantity": "5",
    "positive": "5",
    "negative": "0"
  },
  {
    "created_date": "2023-07-17",
    "quantity": "12",
    "positive": "9",
    "negative": "0"
  },
  {
    "created_date": "2023-07-18",
    "quantity": "13",
    "positive": "8",
    "negative": "4"
  },
  {
    "created_date": "2023-07-19",
    "quantity": "9",
    "positive": "7",
    "negative": "2"
  },
  {
    "created_date": "2023-07-20",
    "quantity": "7",
    "positive": "1",
    "negative": "1"
  },
  {
    "created_date": "2023-07-21",
    "quantity": "4",
    "positive": "4",
    "negative": "0"
  },
  {
    "created_date": "2023-07-22",
    "quantity": "20",
    "positive": "4",
    "negative": "4"
  },
  {
    "created_date": "2023-07-23",
    "quantity": "3",
    "positive": "3",
    "negative": "0"
  },
  {
    "created_date": "2023-07-24",
    "quantity": "12",
    "positive": "9",
    "negative": "1"
  },
  {
    "created_date": "2023-07-25",
    "quantity": "11",
    "positive": "0",
    "negative": "0"
  },
  {
    "created_date": "2023-07-26",
    "quantity": "8",
    "positive": "8",
    "negative": "0"
  },
  {
    "created_date": "2023-07-27",
    "quantity": "6",
    "positive": "6",
    "negative": "0"
  },
  {
    "created_date": "2023-07-28",
    "quantity": "13",
    "positive": "3",
    "negative": "3"
  },
  {
    "created_date": "2023-07-29",
    "quantity": "8",
    "positive": "0",
    "negative": "0"
  },
  {
    "created_date": "2023-07-30",
    "quantity": "4",
    "positive": "2",
    "negative": "1"
  },
  {
    "created_date": "2023-07-31",
    "quantity": "7",
    "positive": "7",
    "negative": "0"
  },
  {
    "created_date": "2023-08-01",
    "quantity": "8",
    "positive": "7",
    "negative": "0"
  },
  {
    "created_date": "2023-08-02",
    "quantity": "7",
    "positive": "4",
    "negative": "0"
  },
  {
    "created_date": "2023-08-03",
    "quantity": "7",
    "positive": "4",
    "negative": "0"
  },
  {
    "created_date": "2023-08-04",
    "quantity": "2",
    "positive": "2",
    "negative": "0"
  },
  {
    "created_date": "2023-08-05",
    "quantity": "17",
    "positive": "13",
    "negative": "1"
  },
  {
    "created_date": "2023-08-06",
    "quantity": "14",
    "positive": "6",
    "negative": "6"
  },
  {
    "created_date": "2023-08-07",
    "quantity": "18",
    "positive": "2",
    "negative": "2"
  },
  {
    "created_date": "2023-08-08",
    "quantity": "6",
    "positive": "0",
    "negative": "0"
  },
  {
    "created_date": "2023-08-09",
    "quantity": "2",
    "positive": "2",
    "negative": "0"
  },
  {
    "created_date": "2023-08-10",
    "quantity": "7",
    "positive": "6",
    "negative": "1"
  },
  {
    "created_date": "2023-08-11",
    "quantity": "6",
    "positive": "6",
    "negative": "0"
  },
  {
    "created_date": "2023-08-12",
    "quantity": "13",
    "positive": "1",
    "negative": "1"
  },
  {
    "created_date": "2023-08-13",
    "quantity": "8",
    "positive": "1",
    "negative": "1"
  },
  {
    "created_date": "2023-08-14",
    "quantity": "13",
    "positive": "9",
    "negative": "2"
  },
  {
    "created_date": "2023-08-15",
    "quantity": "17",
    "positive": "0",
    "negative": "0"
  },
  {
    "created_date": "2023-08-16",
    "quantity": "8",
    "positive": "8",
    "negative": "0"
  },
  {
    "created_date": "2023-08-17",
    "quantity": "8",
    "positive": "3",
    "negative": "1"
  },
  {
    "created_date": "2023-08-18",
    "quantity": "9",
    "positive": "2",
    "negative": "2"
  },
  {
    "created_date": "2023-08-19",
    "quantity": "11",
    "positive": "9",
    "negative": "0"
  },
  {
    "created_date": "2023-08-20",
    "quantity": "6",
    "positive": "6",
    "negative": "0"
  },
  {
    "created_date": "2023-08-21",
    "quantity": "10",
    "positive": "4",
    "negative": "2"
  },
  {
    "created_date": "2023-08-22",
    "quantity": "7",
    "positive": "7",
    "negative": "0"
  },
  {
    "created_date": "2023-08-23",
    "quantity": "10",
    "positive": "1",
    "negative": "1"
  },
  {
    "created_date": "2023-08-24",
    "quantity": "10",
    "positive": "8",
    "negative": "1"
  },
  {
    "created_date": "2023-08-25",
    "quantity": "7",
    "positive": "7",
    "negative": "0"
  },
  {
    "created_date": "2023-08-26",
    "quantity": "18",
    "positive": "18",
    "negative": "0"
  },
  {
    "created_date": "2023-08-27",
    "quantity": "12",
    "positive": "2",
    "negative": "2"
  },
  {
    "created_date": "2023-08-28",
    "quantity": "17",
    "positive": "4",
    "negative": "4"
  },
  {
    "created_date": "2023-08-29",
    "quantity": "14",
    "positive": "0",
    "negative": "0"
  },
  {
    "created_date": "2023-08-30",
    "quantity": "18",
    "positive": "9",
    "negative": "5"
  },
  {
    "created_date": "2023-08-31",
    "quantity": "3",
    "positive": "3",
    "negative": "0"
  },
  {
    "created_date": "2023-09-01",
    "quantity": "12",
    "positive": "12",
    "negative": "0"
  },
  {
    "created_date": "2023-09-02",
    "quantity": "20",
    "positive": "12",
    "negative": "6"
  },
  {
    "created_date": "2023-09-03",
    "quantity": "8",
    "positive": "0",
    "negative": "0"
  },
  {
    "created_date": "2023-09-04",
    "quantity": "6",
    "positive": "6",
    "negative": "0"
  },
  {
    "created_date": "2023-09-05",
    "quantity": "8",
    "positive": "6",
    "negative": "2"
  },
  {
    "created_date": "2023-09-06",
    "quantity": "8",
    "positive": "0",
    "negative": "0"
  },
  {
    "created_date": "2023-09-07",
    "quantity": "7",
    "positive": "6",
    "negative": "0"
  },
  {
    "created_date": "2023-09-08",
    "quantity": "8",
    "positive": "8",
    "negative": "0"
  },
  {
    "created_date": "2023-09-09",
    "quantity": "16",
    "positive": "15",
    "negative": "0"
  },
  {
    "created_date": "2023-09-10",
    "quantity": "2",
    "positive": "0",
    "negative": "0"
  },
  {
    "created_date": "2023-09-11",
    "quantity": "7",
    "positive": "0",
    "negative": "0"
  },
  {
    "created_date": "2023-09-12",
    "quantity": "7",
    "positive": "7",
    "negative": "0"
  },
  {
    "created_date": "2023-09-13",
    "quantity": "9",
    "positive": "5",
    "negative": "0"
  },
  {
    "created_date": "2023-09-14",
    "quantity": "7",
    "positive": "7",
    "negative": "0"
  },
  {
    "created_date": "2023-09-15",
    "quantity": "3",
    "positive": "3",
    "negative": "0"
  },
  {
    "created_date": "2023-09-16",
    "quantity": "14",
    "positive": "14",
    "negative": "0"
  },
  {
    "created_date": "2023-09-17",
    "quantity": "8",
    "positive": "5",
    "negative": "2"
  },
  {
    "created_date": "2023-09-18",
    "quantity": "5",
    "positive": "5",
    "negative": "0"
  },
  {
    "created_date": "2023-09-19",
    "quantity": "11",
    "positive": "7",
    "negative": "1"
  },
  {
    "created_date": "2023-09-20",
    "quantity": "6",
    "positive": "4",
    "negative": "0"
  },
  {
    "created_date": "2023-09-21",
    "quantity": "3",
    "positive": "2",
    "negative": "1"
  },
  {
    "created_date": "2023-09-22",
    "quantity": "5",
    "positive": "1",
    "negative": "1"
  },
  {
    "created_date": "2023-09-23",
    "quantity": "7",
    "positive": "7",
    "negative": "0"
  },
  {
    "created_date": "2023-09-24",
    "quantity": "2",
    "positive": "2",
    "negative": "0"
  },
  {
    "created_date": "2023-09-25",
    "quantity": "19",
    "positive": "14",
    "negative": "4"
  },
  {
    "created_date": "2023-09-26",
    "quantity": "7",
    "positive": "6",
    "negative": "1"
  },
  {
    "created_date": "2023-09-27",
    "quantity": "8",
    "positive": "6",
    "negative": "2"
  },
  {
    "created_date": "2023-09-28",
    "quantity": "6",
    "positive": "1",
    "negative": "1"
  },
  {
    "created_date": "2023-09-29",
    "quantity": "7",
    "positive": "7",
    "negative": "0"
  },
  {
    "created_date": "2023-09-30",
    "quantity": "13",
    "positive": "2",
    "negative": "2"
  },
  {
    "created_date": "2023-10-01",
    "quantity": "6",
    "positive": "6",
    "negative": "0"
  },
  {
    "created_date": "2023-10-02",
    "quantity": "13",
    "positive": "6",
    "negative": "3"
  },
  {
    "created_date": "2023-10-03",
    "quantity": "10",
    "positive": "3",
    "negative": "1"
  },
  {
    "created_date": "2023-10-04",
    "quantity": "10",
    "positive": "0",
    "negative": "0"
  },
  {
    "created_date": "2023-10-05",
    "quantity": "8",
    "positive": "7",
    "negative": "0"
  },
  {
    "created_date": "2023-10-06",
    "quantity": "3",
    "positive": "3",
    "negative": "0"
  },
  {
    "created_date": "2023-10-07",
    "quantity": "12",
    "positive": "12",
    "negative": "0"
  },
  {
    "created_date": "2023-10-08",
    "quantity": "3",
    "positive": "2",
    "negative": "0"
  },
  {
    "created_date": "2023-10-09",
    "quantity": "8",
    "positive": "8",
    "negative": "0"
  },
  {
    "created_date": "2023-10-10",
    "quantity": "14",
    "positive": "14",
    "negative": "0"
  },
  {
    "created_date": "2023-10-11",
    "quantity": "8",
    "positive": "7",
    "negative": "1"
  },
  {
    "created_date": "2023-10-12",
    "quantity": "7",
    "positive": "2",
    "negative": "1"
  },
  {
    "created_date": "2023-10-13",
    "quantity": "4",
    "positive": "4",
    "negative": "0"
  },
  {
    "created_date": "2023-10-14",
    "quantity": "16",
    "positive": "13",
    "negative": "3"
  },
  {
    "created_date": "2023-10-15",
    "quantity": "6",
    "positive": "6",
    "negative": "0"
  },
  {
    "created_date": "2023-10-16",
    "quantity": "14",
    "positive": "8",
    "negative": "6"
  },
  {
    "created_date": "2023-10-17",
    "quantity": "11",
    "positive": "3",
    "negative": "3"
  },
  {
    "created_date": "2023-10-18",
    "quantity": "10",
    "positive": "1",
    "negative": "1"
  },
  {
    "created_date": "2023-10-19",
    "quantity": "6",
    "positive": "0",
    "negative": "0"
  },
  {
    "created_date": "2023-10-20",
    "quantity": "6",
    "positive": "6",
    "negative": "0"
  },
  {
    "created_date": "2023-10-21",
    "quantity": "25",
    "positive": "6",
    "negative": "6"
  },
  {
    "created_date": "2023-10-22",
    "quantity": "13",
    "positive": "11",
    "negative": "1"
  },
  {
    "created_date": "2023-10-23",
    "quantity": "5",
    "positive": "3",
    "negative": "2"
  },
  {
    "created_date": "2023-10-24",
    "quantity": "4",
    "positive": "2",
    "negative": "1"
  },
  {
    "created_date": "2023-10-25",
    "quantity": "8",
    "positive": "5",
    "negative": "2"
  },
  {
    "created_date": "2023-10-26",
    "quantity": "0",
    "positive": "0",
    "negative": "0"
  },
  {
    "created_date": "2023-10-27",
    "quantity": "5",
    "positive": "5",
    "negative": "0"
  },
  {
    "created_date": "2023-10-28",
    "quantity": "16",
    "positive": "1",
    "negative": "1"
  },
  {
    "created_date": "2023-10-29",
    "quantity": "4",
    "positive": "4",
    "negative": "0"
  },
  {
    "created_date": "2023-10-30",
    "quantity": "14",
    "positive": "2",
    "negative": "1"
  },
  {
    "created_date": "2023-10-31",
    "quantity": "8",
    "positive": "8",
    "negative": "0"
  },
  {
    "created_date": "2023-11-01",
    "quantity": "9",
    "positive": "8",
    "negative": "0"
  },
  {
    "created_date": "2023-11-02",
    "quantity": "7",
    "positive": "2",
    "negative": "1"
  },
  {
    "created_date": "2023-11-03",
    "quantity": "8",
    "positive": "8",
    "negative": "0"
  },
  {
    "created_date": "2023-11-04",
    "quantity": "17",
    "positive": "7",
    "negative": "7"
  },
  {
    "created_date": "2023-11-05",
    "quantity": "7",
    "positive": "1",
    "negative": "0"
  },
  {
    "created_date": "2023-11-06",
    "quantity": "12",
    "positive": "1",
    "negative": "1"
  },
  {
    "created_date": "2023-11-07",
    "quantity": "5",
    "positive": "3",
    "negative": "0"
  },
  {
    "created_date": "2023-11-08",
    "quantity": "10",
    "positive": "9",
    "negative": "0"
  },
  {
    "created_date": "2023-11-09",
    "quantity": "5",
    "positive": "2",
    "negative": "0"
  },
  {
    "created_date": "2023-11-10",
    "quantity": "7",
    "positive": "1",
    "negative": "1"
  },
  {
    "created_date": "2023-11-11",
    "quantity": "11",
    "positive": "5",
    "negative": "2"
  },
  {
    "created_date": "2023-11-12",
    "quantity": "7",
    "positive": "3",
    "negative": "3"
  },
  {
    "created_date": "2023-11-13",
    "quantity": "7",
    "positive": "5",
    "negative": "2"
  },
  {
    "created_date": "2023-11-14",
    "quantity": "10",
    "positive": "8",
    "negative": "2"
  },
  {
    "created_date": "2023-11-15",
    "quantity": "7",
    "positive": "0",
    "negative": "0"
  },
  {
    "created_date": "2023-11-16",
    "quantity": "7",
    "positive": "1",
    "negative": "1"
  },
  {
    "created_date": "2023-11-17",
    "quantity": "5",
    "positive": "3",
    "negative": "1"
  },
  {
    "created_date": "2023-11-18",
    "quantity": "8",
    "positive": "5",
    "negative": "3"
  },
  {
    "created_date": "2023-11-19",
    "quantity": "4",
    "positive": "4",
    "negative": "0"
  },
  {
    "created_date": "2023-11-20",
    "quantity": "12",
    "positive": "9",
    "negative": "0"
  },
  {
    "created_date": "2023-11-21",
    "quantity": "7",
    "positive": "7",
    "negative": "0"
  },
  {
    "created_date": "2023-11-22",
    "quantity": "8",
    "positive": "5",
    "negative": "3"
  },
  {
    "created_date": "2023-11-23",
    "quantity": "9",
    "positive": "2",
    "negative": "0"
  },
  {
    "created_date": "2023-11-24",
    "quantity": "5",
    "positive": "5",
    "negative": "0"
  },
  {
    "created_date": "2023-11-25",
    "quantity": "13",
    "positive": "12",
    "negative": "1"
  },
  {
    "created_date": "2023-11-26",
    "quantity": "7",
    "positive": "7",
    "negative": "0"
  },
  {
    "created_date": "2023-11-27",
    "quantity": "13",
    "positive": "12",
    "negative": "1"
  },
  {
    "created_date": "2023-11-28",
    "quantity": "10",
    "positive": "2",
    "negative": "2"
  },
  {
    "created_date": "2023-11-29",
    "quantity": "3",
    "positive": "3",
    "negative": "0"
  },
  {
    "created_date": "2023-11-30",
    "quantity": "9",
    "positive": "0",
    "negative": "0"
  },
  {
    "created_date": "2023-12-01",
    "quantity": "5",
    "positive": "5",
    "negative": "0"
  },
  {
    "created_date": "2023-12-02",
    "quantity": "11",
    "positive": "6",
    "negative": "1"
  },
  {
    "created_date": "2023-12-03",
    "quantity": "7",
    "positive": "6",
    "negative": "1"
  },
  {
    "created_date": "2023-12-04",
    "quantity": "5",
    "positive": "5",
    "negative": "0"
  },
  {
    "created_date": "2023-12-05",
    "quantity": "11",
    "positive": "6",
    "negative": "1"
  },
  {
    "created_date": "2023-12-06",
    "quantity": "6",
    "positive": "0",
    "negative": "0"
  },
  {
    "created_date": "2023-12-07",
    "quantity": "3",
    "positive": "0",
    "negative": "0"
  },
  {
    "created_date": "2023-12-08",
    "quantity": "6",
    "positive": "6",
    "negative": "0"
  },
  {
    "created_date": "2023-12-09",
    "quantity": "12",
    "positive": "12",
    "negative": "0"
  },
  {
    "created_date": "2023-12-10",
    "quantity": "6",
    "positive": "6",
    "negative": "0"
  },
  {
    "created_date": "2023-12-11",
    "quantity": "12",
    "positive": "11",
    "negative": "0"
  },
  {
    "created_date": "2023-12-12",
    "quantity": "9",
    "positive": "1",
    "negative": "0"
  },
  {
    "created_date": "2023-12-13",
    "quantity": "9",
    "positive": "9",
    "negative": "0"
  },
  {
    "created_date": "2023-12-14",
    "quantity": "15",
    "positive": "12",
    "negative": "2"
  },
  {
    "created_date": "2023-12-15",
    "quantity": "5",
    "positive": "5",
    "negative": "0"
  },
  {
    "created_date": "2023-12-16",
    "quantity": "14",
    "positive": "9",
    "negative": "5"
  },
  {
    "created_date": "2023-12-17",
    "quantity": "7",
    "positive": "7",
    "negative": "0"
  },
  {
    "created_date": "2023-12-18",
    "quantity": "17",
    "positive": "7",
    "negative": "7"
  },
  {
    "created_date": "2023-12-19",
    "quantity": "6",
    "positive": "5",
    "negative": "1"
  },
  {
    "created_date": "2023-12-20",
    "quantity": "11",
    "positive": "8",
    "negative": "1"
  },
  {
    "created_date": "2023-12-21",
    "quantity": "4",
    "positive": "2",
    "negative": "0"
  },
  {
    "created_date": "2023-12-22",
    "quantity": "8",
    "positive": "4",
    "negative": "2"
  },
  {
    "created_date": "2023-12-23",
    "quantity": "9",
    "positive": "1",
    "negative": "1"
  },
  {
    "created_date": "2023-12-24",
    "quantity": "8",
    "positive": "7",
    "negative": "1"
  },
  {
    "created_date": "2023-12-25",
    "quantity": "7",
    "positive": "6",
    "negative": "0"
  },
  {
    "created_date": "2023-12-26",
    "quantity": "9",
    "positive": "4",
    "negative": "1"
  },
  {
    "created_date": "2023-12-27",
    "quantity": "12",
    "positive": "8",
    "negative": "2"
  },
  {
    "created_date": "2023-12-28",
    "quantity": "8",
    "positive": "7",
    "negative": "0"
  },
  {
    "created_date": "2023-12-29",
    "quantity": "10",
    "positive": "10",
    "negative": "0"
  },
  {
    "created_date": "2023-12-30",
    "quantity": "16",
    "positive": "4",
    "negative": "2"
  },
  {
    "created_date": "2023-12-31",
    "quantity": "2",
    "positive": "2",
    "negative": "0"
  }
]